{"stats":{"minecraft:used":{"minecraft:nether_brick_fence":1543,"minecraft:light_blue_stained_glass_pane":47,"minecraft:blue_terracotta":32,"minecraft:writable_book":1,"minecraft:red_sand":13,"minecraft:light_gray_stained_glass_pane":206,"minecraft:spruce_slab":103,"minecraft:red_sandstone_slab":1637,"minecraft:dispenser":8,"minecraft:poppy":181,"minecraft:dead_brain_coral":50,"minecraft:bone_block":8,"minecraft:ladder":631,"minecraft:white_concrete_powder":2054,"minecraft:chest":18,"minecraft:white_terracotta":47013,"minecraft:stone":50741,"minecraft:quartz_stairs":1395,"minecraft:grass":1898,"minecraft:player_head":14,"minecraft:farmland":4,"minecraft:debug_stick":12,"minecraft:chiseled_red_sandstone":2,"minecraft:soul_sand":159,"minecraft:orange_glazed_terracotta":220,"minecraft:nether_bricks":5023,"minecraft:jungle_slab":149,"minecraft:orange_wool":2039,"minecraft:pink_terracotta":4,"minecraft:cyan_wool":102,"minecraft:azure_bluet":13,"minecraft:stripped_spruce_log":57,"minecraft:obsidian":22,"minecraft:red_sandstone_stairs":984,"minecraft:spruce_boat":2,"minecraft:glass":1057,"minecraft:packed_ice":1,"minecraft:lava_bucket":25,"minecraft:bricks":1928,"minecraft:stripped_dark_oak_wood":3,"minecraft:red_wool":2138,"minecraft:jungle_fence_gate":2,"minecraft:quartz_slab":48,"minecraft:black_stained_glass_pane":222,"minecraft:grass_block":1046,"minecraft:orange_shulker_box":81,"minecraft:green_wool":41,"minecraft:quartz_block":19193,"minecraft:wet_sponge":49,"minecraft:dark_oak_slab":6,"minecraft:gray_concrete_powder":80,"minecraft:pink_wool":1,"minecraft:stone_brick_stairs":3198,"minecraft:stone_bricks":3985,"minecraft:item_frame":122,"minecraft:bedrock":812,"minecraft:repeater":37,"minecraft:redstone_lamp":741,"minecraft:magma_block":13,"minecraft:brown_carpet":3,"minecraft:written_book":3,"minecraft:yellow_glazed_terracotta":3,"minecraft:blue_shulker_box":3,"minecraft:furnace":68,"minecraft:acacia_fence":689,"minecraft:gold_block":87,"minecraft:skeleton_skull":444,"minecraft:gray_banner":205,"minecraft:magenta_shulker_box":412,"minecraft:stripped_spruce_wood":14,"minecraft:dark_oak_stairs":548,"minecraft:end_rod":627,"minecraft:diorite":169,"minecraft:ink_sac":250,"minecraft:end_stone_bricks":4244,"minecraft:spruce_door":717,"minecraft:dropper":2338,"minecraft:stripped_acacia_log":105,"minecraft:infested_stone":693,"minecraft:acacia_trapdoor":332,"minecraft:gray_carpet":262,"minecraft:jungle_fence":163,"minecraft:oak_planks":1925,"minecraft:wooden_pickaxe":1,"minecraft:sandstone":637,"minecraft:black_glazed_terracotta":620,"minecraft:redstone_block":115,"minecraft:clay":1043,"minecraft:sugar_cane":60,"minecraft:purpur_pillar":202,"minecraft:oak_leaves":5527,"minecraft:white_wool":111439,"minecraft:dark_oak_trapdoor":327,"minecraft:sand":563,"minecraft:purpur_stairs":98,"minecraft:infested_chiseled_stone_bricks":685,"minecraft:smooth_red_sandstone":36,"minecraft:black_banner":1230,"minecraft:light_gray_terracotta":8,"minecraft:yellow_concrete":737,"minecraft:dead_bubble_coral":4,"minecraft:sponge":2123,"minecraft:chiseled_quartz_block":106,"minecraft:note_block":134,"minecraft:gray_concrete":51,"minecraft:end_stone":20,"minecraft:birch_fence":2,"minecraft:redstone_torch":708,"minecraft:black_terracotta":21,"minecraft:sticky_piston":4,"minecraft:lever":345,"minecraft:green_concrete":8,"minecraft:red_sandstone":6489,"minecraft:firework_rocket":2814,"minecraft:daylight_detector":10,"minecraft:acacia_door":407,"minecraft:dark_oak_log":33,"minecraft:gray_shulker_box":84,"minecraft:light_gray_concrete":151,"minecraft:birch_slab":2,"minecraft:heavy_weighted_pressure_plate":40,"minecraft:barrier":274,"minecraft:stone_button":1124,"minecraft:white_glazed_terracotta":142,"minecraft:sign":2614,"minecraft:red_terracotta":16,"minecraft:polished_granite":10,"minecraft:oak_pressure_plate":105,"minecraft:iron_door":858,"minecraft:cut_red_sandstone":185,"minecraft:gravel":2196,"minecraft:dead_horn_coral":10,"minecraft:nether_wart_block":1076,"minecraft:coal_block":1004,"minecraft:stripped_oak_wood":532,"minecraft:dark_oak_fence":3,"minecraft:white_stained_glass":11158,"minecraft:andesite":75,"minecraft:mossy_cobblestone_wall":349,"minecraft:white_concrete":27549,"minecraft:coarse_dirt":1947,"minecraft:cobweb":1802,"minecraft:gray_stained_glass":7,"minecraft:oak_fence":611,"minecraft:oak_trapdoor":1202,"minecraft:purpur_block":4543,"minecraft:stripped_acacia_wood":5,"minecraft:jungle_leaves":391,"minecraft:iron_bars":9549,"minecraft:acacia_log":130,"minecraft:orange_concrete":190,"minecraft:dead_bush":403,"minecraft:white_tulip":8,"minecraft:carved_pumpkin":7,"minecraft:armor_stand":1,"minecraft:red_concrete":6,"minecraft:redstone":119,"minecraft:light_gray_carpet":383,"minecraft:mycelium":77,"minecraft:spruce_planks":50,"minecraft:brown_shulker_box":19,"minecraft:dried_kelp_block":8,"minecraft:light_gray_shulker_box":456,"minecraft:oak_door":549,"minecraft:torch":1239,"minecraft:brewing_stand":19,"minecraft:dirt":10072,"minecraft:anvil":204,"minecraft:white_carpet":5012,"minecraft:hopper":187,"minecraft:spruce_stairs":831,"minecraft:cobblestone_wall":8812,"minecraft:dead_tube_coral":17,"minecraft:shulker_box":16,"minecraft:light_gray_glazed_terracotta":1372,"minecraft:yellow_carpet":68,"minecraft:jungle_trapdoor":201,"minecraft:granite":7,"minecraft:spruce_fence":315,"minecraft:dead_brain_coral_block":420,"minecraft:nether_brick_stairs":619,"minecraft:oak_fence_gate":68,"minecraft:polished_diorite":176,"minecraft:fern":481,"minecraft:birch_door":13,"minecraft:stone_brick_slab":145,"minecraft:brown_terracotta":9,"minecraft:sea_lantern":29,"minecraft:red_tulip":10,"minecraft:light_gray_stained_glass":117,"minecraft:bookshelf":162,"minecraft:iron_block":627,"minecraft:light_weighted_pressure_plate":8,"minecraft:oak_stairs":408,"minecraft:slime_block":14,"minecraft:brick_stairs":106,"minecraft:jungle_log":30,"minecraft:prismarine_slab":4,"minecraft:light_gray_wool":432,"minecraft:tripwire_hook":79,"minecraft:glowstone":6874,"minecraft:lime_concrete":1,"minecraft:gray_glazed_terracotta":853,"minecraft:black_stained_glass":1,"minecraft:magenta_wool":76,"minecraft:tall_grass":25,"minecraft:emerald_block":2988,"minecraft:iron_trapdoor":5704,"minecraft:white_stained_glass_pane":13706,"minecraft:podzol":2,"minecraft:minecart":8,"minecraft:stone_pressure_plate":899,"minecraft:dead_bubble_coral_block":16,"minecraft:orange_stained_glass_pane":1,"minecraft:observer":31,"minecraft:orange_terracotta":212,"minecraft:water_bucket":264,"minecraft:light_blue_glazed_terracotta":4,"minecraft:cobblestone_stairs":2643,"minecraft:sandstone_stairs":286,"minecraft:yellow_shulker_box":14,"minecraft:polished_andesite":92,"minecraft:lime_wool":3999,"minecraft:red_nether_bricks":3889,"minecraft:blue_wool":8,"minecraft:black_shulker_box":15,"minecraft:cut_sandstone":7,"minecraft:cauldron":777,"minecraft:cobblestone_slab":1227,"minecraft:spruce_fence_gate":76,"minecraft:pink_concrete":2,"minecraft:diamond_block":8,"minecraft:light_gray_banner":29,"minecraft:rail":2690,"minecraft:terracotta":840,"minecraft:vine":370,"minecraft:tnt":14,"minecraft:oak_slab":3641,"minecraft:crafting_table":66,"minecraft:dead_fire_coral_block":41,"minecraft:white_bed":63,"minecraft:light_gray_concrete_powder":2,"minecraft:dark_oak_fence_gate":3,"minecraft:lime_shulker_box":46,"minecraft:painting":554,"minecraft:dark_oak_door":66,"minecraft:oak_log":7108,"minecraft:gray_terracotta":327,"minecraft:piston":54,"minecraft:flower_pot":83,"minecraft:activator_rail":10,"minecraft:acacia_stairs":268,"minecraft:black_wool":250,"minecraft:dead_fire_coral":216,"minecraft:command_block":154,"minecraft:sunflower":446,"minecraft:oak_button":185,"minecraft:map":3,"minecraft:jungle_stairs":121,"minecraft:cyan_concrete":29,"minecraft:stone_slab":95035,"minecraft:purpur_slab":197,"minecraft:spruce_trapdoor":21,"minecraft:yellow_wool":37,"minecraft:chiseled_stone_bricks":39,"minecraft:green_shulker_box":22,"minecraft:cobblestone":5315,"minecraft:orange_banner":40,"minecraft:sandstone_slab":8,"minecraft:jungle_door":55,"minecraft:pink_shulker_box":31,"minecraft:lapis_block":1055,"minecraft:glass_pane":1288,"minecraft:end_portal_frame":13,"minecraft:stripped_oak_log":3,"minecraft:gray_wool":226,"minecraft:smooth_stone":194,"minecraft:birch_stairs":54},"minecraft:dropped":{"minecraft:piston":1,"minecraft:oak_pressure_plate":1,"minecraft:sandstone_stairs":1,"minecraft:bedrock":1,"minecraft:cobblestone_stairs":2,"minecraft:redstone_lamp":1,"minecraft:birch_fence":1,"minecraft:stone_button":2,"minecraft:white_stained_glass_pane":4,"minecraft:writable_book":1,"minecraft:dark_oak_planks":1,"minecraft:white_wool":19,"minecraft:purpur_block":1,"minecraft:lever":4,"minecraft:mycelium":1,"minecraft:skeleton_skull":23,"minecraft:dropper":2,"minecraft:quartz_block":4,"minecraft:hopper":1,"minecraft:glowstone":1,"minecraft:stone_brick_stairs":2,"minecraft:oak_leaves":1,"minecraft:firework_rocket":32,"minecraft:oak_slab":1,"minecraft:cobblestone":1,"minecraft:command_block":27,"minecraft:grass_block":1,"minecraft:sign":2,"minecraft:cobweb":1,"minecraft:iron_block":1,"minecraft:iron_trapdoor":2,"minecraft:sponge":3,"minecraft:torch":1,"minecraft:wooden_axe":4,"minecraft:nether_wart_block":1,"minecraft:white_concrete":3,"minecraft:yellow_shulker_box":1,"minecraft:iron_door":1,"minecraft:furnace":1,"minecraft:cobblestone_wall":7,"minecraft:white_carpet":3,"minecraft:stone_slab":12,"minecraft:white_terracotta":11,"minecraft:glass_pane":1,"minecraft:filled_map":1,"minecraft:stone":7,"minecraft:stone_pressure_plate":1,"minecraft:red_sandstone_stairs":1,"minecraft:white_stained_glass":3},"minecraft:picked_up":{"minecraft:wooden_axe":4,"minecraft:red_sandstone_stairs":1,"minecraft:stone_slab":4,"minecraft:stone_brick_stairs":1,"minecraft:written_book":1,"minecraft:iron_boots":1,"minecraft:orange_shulker_box":1,"minecraft:torch":1,"minecraft:quartz_block":2,"minecraft:white_terracotta":8,"minecraft:cobblestone":1,"minecraft:sponge":1,"minecraft:iron_door":2,"minecraft:dropper":2,"minecraft:lever":1,"minecraft:white_concrete":1,"minecraft:oak_leaves":1,"minecraft:end_stone_bricks":1,"minecraft:purpur_block":1,"minecraft:compass":2,"minecraft:white_carpet":1,"minecraft:item_frame":4,"minecraft:white_stained_glass":1,"minecraft:glass_pane":1,"minecraft:stone":2,"minecraft:stone_button":1,"minecraft:black_banner":4,"minecraft:skeleton_skull":2,"minecraft:white_wool":5,"minecraft:filled_map":4,"minecraft:gunpowder":2,"minecraft:cobblestone_stairs":1,"minecraft:paper":10,"minecraft:apple":1,"minecraft:white_stained_glass_pane":4,"minecraft:firework_rocket":384,"minecraft:painting":15},"minecraft:mined":{"minecraft:stone":1},"minecraft:crafted":{"minecraft:wooden_pickaxe":1},"minecraft:custom":{"minecraft:interact_with_crafting_table":25,"minecraft:open_shulker_box":43,"minecraft:leave_game":892,"minecraft:time_since_death":5431194,"minecraft:sprint_one_cm":4558155,"minecraft:drop":174,"minecraft:deaths":4,"minecraft:jump":26948,"minecraft:walk_on_water_one_cm":352095,"minecraft:interact_with_furnace":8,"minecraft:play_one_minute":62361927,"minecraft:open_enderchest":1,"minecraft:damage_dealt":10,"minecraft:interact_with_beacon":1,"minecraft:crouch_one_cm":1150500,"minecraft:inspect_dispenser":6,"minecraft:inspect_dropper":48,"minecraft:inspect_hopper":15,"minecraft:climb_one_cm":70162,"minecraft:walk_one_cm":9778372,"minecraft:sneak_time":2103017,"minecraft:walk_under_water_one_cm":365224,"minecraft:boat_one_cm":131377,"minecraft:tune_noteblock":17,"minecraft:pot_flower":32,"minecraft:time_since_rest":5431224,"minecraft:damage_taken":1160,"minecraft:trigger_trapped_chest":4,"minecraft:swim_one_cm":16157,"minecraft:fly_one_cm":922083583,"minecraft:open_chest":55,"minecraft:aviate_one_cm":14151853,"minecraft:fall_one_cm":12399}},"DataVersion":1631}